{
  "live_ad": "admob",
  "admob": {
    "app_id": "ca-app-pub-3940256099942544~3347511713",
    "interstitial": "/22405025169,22479221618/freemusic.musicapp.music.player.musicplayer.Interstitial",
    "native_advance": "/22405025169,22479221618/freemusic.musicapp.music.player.musicplayer.Native",
    "app_open_ad": "/22405025169,22479221618/freemusic.musicapp.music.player.musicplayer.AppOpen"
  },
  "facebook": {
    "interstitial": "296956551955557_296957368622142",
    "native_advance": "296956551955557_296957795288766"
  }
}
